{
  "appVersion": "xxx",
  "appName": "vops-platform-onecx-request-ui",
  "description": "OneCX QuickActionsPanelComponent",
  "remoteBaseUrl": "/mfe/vops-platform-onecx-request/",
  "remoteEntry": "/mfe/vops-platform-onecx-request/remoteEntry.js",
  "note": "Imported MFE",
  "exposedModule": "./QuickActionsPanelComponent",
  "technology": "WEBCOMPONENTMODULE",
  "remoteName": "vops-platform-onecx-request-ui",
  "tagName": "quick-actions-panel-webcomponent",
  "type": "COMPONENT",
  "deprecated": false,
  "undeployed": false
}